{
  "id": "indeedee-f",
  "nid": "0876-f",
  "dexNum": 876,
  "formId": "f",
  "name": "Female Indeedee",
  "psName": "Indeedee-F",
  "formName": "Female",
  "region": "galar",
  "generation": 8,
  "type1": "psychic",
  "type2": "normal",
  "color": "purple",
  "abilities": {
    "primary": "owntempo",
    "secondary": "synchronize",
    "hidden": "psychicsurge"
  },
  "isDefault": false,
  "isForm": true,
  "isLegendary": false,
  "isMythical": false,
  "isUltraBeast": false,
  "ultraBeastCode": null,
  "isSpecialAbilityForm": false,
  "isCosmeticForm": false,
  "isFemaleForm": true,
  "hasGenderDifferences": true,
  "isBattleOnlyForm": false,
  "isSwitchableForm": false,
  "isFusion": false,
  "fusedWith": null,
  "isMega": false,
  "isPrimal": false,
  "isGmax": false,
  "isRegional": false,
  "canGmax": false,
  "canDynamax": true,
  "canBeAlpha": false,
  "debutIn": "swsh",
  "obtainableIn": [
    "swsh",
    "sv"
  ],
  "versionExclusiveIn": [],
  "eventOnlyIn": [],
  "storableIn": [
    "swsh",
    "home",
    "sv"
  ],
  "shinyReleased": true,
  "shinyBase": null,
  "baseStats": {
    "hp": 70,
    "atk": 55,
    "def": 65,
    "spa": 95,
    "spd": 105,
    "spe": 85
  },
  "weight": 2800,
  "height": 90,
  "baseSpecies": "indeedee",
  "baseForms": [],
  "forms": [],
  "evolvesFrom": null,
  "refs": {
    "smogon": "indeedee",
    "showdown": "indeedeef",
    "serebii": "indeedee",
    "bulbapedia": "Indeedee"
  }
}
