{
  "id": "gardevoir",
  "nid": "0282",
  "dexNum": 282,
  "formId": null,
  "name": "Gardevoir",
  "psName": "Gardevoir",
  "formName": null,
  "region": "hoenn",
  "generation": 3,
  "type1": "psychic",
  "type2": "fairy",
  "color": "white",
  "abilities": {
    "primary": "synchronize",
    "secondary": "trace",
    "hidden": "telepathy"
  },
  "isDefault": true,
  "isForm": false,
  "isLegendary": false,
  "isMythical": false,
  "isUltraBeast": false,
  "ultraBeastCode": null,
  "isSpecialAbilityForm": false,
  "isCosmeticForm": false,
  "isFemaleForm": false,
  "hasGenderDifferences": false,
  "isBattleOnlyForm": false,
  "isSwitchableForm": false,
  "isFusion": false,
  "fusedWith": null,
  "isMega": false,
  "isPrimal": false,
  "isGmax": false,
  "isRegional": false,
  "canGmax": false,
  "canDynamax": true,
  "canBeAlpha": true,
  "debutIn": "rs",
  "obtainableIn": [
    "rs",
    "e",
    "oras",
    "go",
    "swsh",
    "bdsp",
    "la",
    "sv"
  ],
  "versionExclusiveIn": [],
  "eventOnlyIn": [],
  "storableIn": [
    "rs",
    "e",
    "frlg",
    "dp",
    "pt",
    "hgss",
    "bw",
    "b2w2",
    "xy",
    "oras",
    "go",
    "sm",
    "usum",
    "swsh",
    "home",
    "bdsp",
    "la",
    "sv"
  ],
  "shinyReleased": true,
  "shinyBase": null,
  "baseStats": {
    "hp": 68,
    "atk": 65,
    "def": 65,
    "spa": 125,
    "spd": 115,
    "spe": 80
  },
  "weight": 4840,
  "height": 160,
  "baseSpecies": null,
  "baseForms": [],
  "forms": [
    "gardevoir-mega"
  ],
  "evolvesFrom": {
    "pokemon": "kirlia",
    "level": 30
  },
  "refs": {
    "smogon": "gardevoir",
    "showdown": "gardevoir",
    "serebii": "gardevoir",
    "bulbapedia": "Gardevoir"
  }
}
