{
  "id": "glalie",
  "nid": "0362",
  "dexNum": 362,
  "formId": null,
  "name": "Glalie",
  "psName": "Glalie",
  "formName": null,
  "region": "hoenn",
  "generation": 3,
  "type1": "ice",
  "type2": null,
  "color": "gray",
  "abilities": {
    "primary": "innerfocus",
    "secondary": "icebody",
    "hidden": "moody"
  },
  "isDefault": true,
  "isForm": false,
  "isLegendary": false,
  "isMythical": false,
  "isUltraBeast": false,
  "ultraBeastCode": null,
  "isSpecialAbilityForm": false,
  "isCosmeticForm": false,
  "isFemaleForm": false,
  "hasGenderDifferences": false,
  "isBattleOnlyForm": false,
  "isSwitchableForm": false,
  "isFusion": false,
  "fusedWith": null,
  "isMega": false,
  "isPrimal": false,
  "isGmax": false,
  "isRegional": false,
  "canGmax": false,
  "canDynamax": true,
  "canBeAlpha": true,
  "debutIn": "rs",
  "obtainableIn": [
    "rs",
    "e",
    "oras",
    "go",
    "swsh",
    "bdsp",
    "la",
    "sv"
  ],
  "versionExclusiveIn": [],
  "eventOnlyIn": [],
  "storableIn": [
    "rs",
    "e",
    "frlg",
    "dp",
    "pt",
    "hgss",
    "bw",
    "b2w2",
    "xy",
    "oras",
    "go",
    "sm",
    "usum",
    "swsh",
    "home",
    "bdsp",
    "la",
    "sv"
  ],
  "shinyReleased": true,
  "shinyBase": null,
  "baseStats": {
    "hp": 80,
    "atk": 80,
    "def": 80,
    "spa": 80,
    "spd": 80,
    "spe": 80
  },
  "weight": 25650,
  "height": 150,
  "baseSpecies": null,
  "baseForms": [],
  "forms": [
    "glalie-mega"
  ],
  "evolvesFrom": {
    "pokemon": "snorunt",
    "level": 42
  },
  "refs": {
    "smogon": "glalie",
    "showdown": "glalie",
    "serebii": "glalie",
    "bulbapedia": "Glalie"
  }
}
