{
  "jap": {
    "name": "アラブルタケ",
    "genus": "パラドックスポケモン",
    "flavorText": []
  },
  "jap_ro": {
    "name": "Araburutake",
    "genus": "",
    "flavorText": []
  },
  "kor": {
    "name": "사나운버섯",
    "genus": "",
    "flavorText": []
  },
  "cht": {
    "name": "猛惡菇",
    "genus": "悖謬寶可夢",
    "flavorText": []
  },
  "fra": {
    "name": "Fongus-Furie",
    "genus": "",
    "flavorText": []
  },
  "deu": {
    "name": "Wutpilz",
    "genus": "Paradox",
    "flavorText": []
  },
  "esp": {
    "name": "Furioseta",
    "genus": "",
    "flavorText": []
  },
  "ita": {
    "name": "Fungofurioso",
    "genus": "",
    "flavorText": []
  },
  "eng": {
    "name": "Brute Bonnet",
    "genus": "Paradox Pokémon",
    "flavorText": [
      {
        "game": "sv-s",
        "text": "It is possible that the creature listed as Brute Bonnet in a certain book could actually be this Pokémon."
      },
      {
        "game": "sv-v",
        "text": "It bears a slight resemblance to a Pokémon described in a dubious magazine as a cross between a dinosaur and a mushroom."
      }
    ]
  },
  "chs": {
    "name": "猛恶菇",
    "genus": "悖谬宝可梦",
    "flavorText": []
  }
}
