{
  "jap": {
    "name": "ケイコウオ",
    "genus": "はねうおポケモン",
    "flavorText": [
      {
        "game": "xy-x",
        "text": "からだの　よこがわにある　ラインは\nたいようのひかりを　ためておける。\nよるになると　あざやかに　かがやく。"
      },
      {
        "game": "xy-y",
        "text": "たいようを　いっぱいに　あびた\nおびれの　もようは　くらくなると\nあざやかな　いろで　ひかりだす。"
      },
      {
        "game": "oras-or",
        "text": "からだの　よこがわにある　ラインは\nたいようのひかりを　ためておける。\nよるになると　あざやかに　かがやく。"
      },
      {
        "game": "oras-as",
        "text": "たいようを　いっぱいに　あびた\nおびれの　もようは　くらくなると\nあざやかな　いろで　ひかりだす。"
      },
      {
        "game": "sm-s",
        "text": "ピンクいろの　かわの　ぶぶんは\nたいようこうを　ためて　ひかる。\nカモフラージュの　ためと　いわれる。"
      },
      {
        "game": "sm-m",
        "text": "２まいの　おビレで　げんきにジャンプ。\nかいめんに　とびあがった　ところを\nキャモメが　くわえ　さらっていく。"
      },
      {
        "game": "usum-us",
        "text": "ピンクいろの　もようは　よるになると\nひかりだす。　ダイバーに　にんきなので\nリゾートちでは　えづけされることも。"
      },
      {
        "game": "usum-um",
        "text": "ひかる　おびれで　えものを　さそう。\nひるは　かいめん　ちかくに　いて\nよるに　なると　ふかみに　いどう。"
      }
    ]
  },
  "jap_ro": {
    "name": "Keikouo",
    "genus": "",
    "flavorText": []
  },
  "kor": {
    "name": "형광어",
    "genus": "비어포켓몬",
    "flavorText": [
      {
        "game": "xy-x",
        "text": "몸의 옆쪽에 있는 줄에\n태양의 빛을 모아둘 수 있다.\n밤이 되면 아름답게 빛난다."
      },
      {
        "game": "xy-y",
        "text": "햇볕을 잔뜩 쬔 꼬리지느러미의\n무늬는 어두워지면 선명한 색으로\n반짝이기 시작한다."
      },
      {
        "game": "oras-or",
        "text": "몸의 옆쪽에 있는 줄에\n태양의 빛을 모아둘 수 있다.\n밤이 되면 아름답게 빛난다."
      },
      {
        "game": "oras-as",
        "text": "햇볕을 잔뜩 쬔 꼬리지느러미의\n무늬는 어두워지면 선명한 색으로\n반짝이기 시작한다."
      },
      {
        "game": "sm-s",
        "text": "핑크색의 가죽 부분은\n태양광을 모아서 빛을 낸다.\n위장하기 위해서라고 전해진다."
      },
      {
        "game": "sm-m",
        "text": "2장의 꼬리지느러미로 힘차게 점프한다.\n해수면을 뛰어오르는 순간\n갈모매가 물고 가버린다."
      },
      {
        "game": "usum-us",
        "text": "핑크색 모양은 밤이 되면 빛이 난다.\n다이버에게 인기여서 리조트에서\n길들여지기도 한다."
      },
      {
        "game": "usum-um",
        "text": "빛나는 꼬리지느러미로 먹이를 유인한다.\n낮에는 해수면 가까이 있다가\n밤이 되면 깊은 곳으로 이동한다."
      }
    ]
  },
  "cht": {
    "name": "螢光魚",
    "genus": "飛翅魚寶可夢",
    "flavorText": [
      {
        "game": "sm-s",
        "text": "粉紅色的皮膚部分\n會儲存太陽光發光。\n聽說是用來做保護色的。"
      },
      {
        "game": "sm-m",
        "text": "用２枚尾鰭活力充沛地跳躍。\n跳出海面的那一刻，\n會被長翅鷗叼走。"
      },
      {
        "game": "usum-us",
        "text": "粉紅色的花紋到了夜裡就會發光。\n由於很受潛水者的歡迎，\n在度假地有時會被人工馴養。"
      },
      {
        "game": "usum-um",
        "text": "會用發光的尾鰭引誘獵物。\n白天會待在海面附近，\n到了夜裡就會向深海移動。"
      }
    ]
  },
  "fra": {
    "name": "Écayon",
    "genus": "Pokémon Poisson Ailé",
    "flavorText": [
      {
        "game": "bw-b",
        "text": "La ligne qui fait le tour de son\ncorps stocke l’énergie solaire\net brille dans la nuit."
      },
      {
        "game": "bw-w",
        "text": "La ligne qui fait le tour de son\ncorps stocke l’énergie solaire\net brille dans la nuit."
      },
      {
        "game": "xy-x",
        "text": "La ligne qui fait le tour de son corps stocke l’énergie\nsolaire et brille dans la nuit."
      },
      {
        "game": "xy-y",
        "text": "Après une longue exposition au soleil, les motifs de\nses nageoires caudales luisent à la nuit tombée."
      },
      {
        "game": "oras-or",
        "text": "La ligne qui fait le tour de son corps stocke l’énergie solaire\net brille dans la nuit."
      },
      {
        "game": "oras-as",
        "text": "Après une longue exposition au soleil, les motifs de\nses nageoires caudales luisent à la nuit tombée."
      },
      {
        "game": "sm-s",
        "text": "Il stocke les rayons solaires grâce aux parties\nroses de sa peau, qui brillent ensuite. Il s’agirait\nen fait d’une technique de camouflage."
      },
      {
        "game": "sm-m",
        "text": "Avec sa double nageoire caudale, il peut bondir\nhors de l’eau. C’est souvent à ce moment que\nles Goélise de passage l’attrapent et le gobent."
      },
      {
        "game": "usum-us",
        "text": "Les motifs roses de sa peau brillent la nuit.\nDes stations balnéaires l’attirent avec de la\nnourriture, car il est très aimé des plongeurs."
      },
      {
        "game": "usum-um",
        "text": "Il attire ses proies avec ses nageoires caudales\nlumineuses. Il passe la journée à la surface\net se retire dans les abysses la nuit venue."
      }
    ]
  },
  "deu": {
    "name": "Finneon",
    "genus": "Flügelfisch",
    "flavorText": [
      {
        "game": "xy-x",
        "text": "Die Linie an seiner Seite kann Sonnenlicht\nspeichern. Nachts leuchtet es sehr intensiv."
      },
      {
        "game": "xy-y",
        "text": "Wurden die Flossen lange dem Sonnenlicht\nausgesetzt, leuchten sie in der Dunkelheit."
      },
      {
        "game": "oras-or",
        "text": "Die Linie an seiner Seite kann Sonnenlicht speichern.\nNachts leuchtet es sehr intensiv."
      },
      {
        "game": "oras-as",
        "text": "Wurden die Flossen lange dem Sonnenlicht ausgesetzt,\nleuchten sie in der Dunkelheit."
      },
      {
        "game": "sm-s",
        "text": "Der rosafarbene Teil seiner Haut speichert\nSonnenlicht und leuchtet. Es wird angenommen,\ndass dies der Tarnung dient."
      },
      {
        "game": "sm-m",
        "text": "Mit ihren beiden Flossen können sie hoch in die\nLuft springen. Über der Meeresoberfläche lauern\njedoch Wingull."
      },
      {
        "game": "usum-us",
        "text": "Seine rosafarbene Musterung leuchtet in der\nNacht. Wegen seiner Popularität unter Tauchern\nist es ein gern gesehener Gast in Feriengebieten."
      },
      {
        "game": "usum-um",
        "text": "Seine leuchtenden Flossen locken Beute an. Bei\nTag bleibt es nahe an der Wasseroberfläche,\nwährend es abends in den Tiefen verschwindet."
      }
    ]
  },
  "esp": {
    "name": "Finneon",
    "genus": "Pokémon Pez Ala",
    "flavorText": [
      {
        "game": "xy-x",
        "text": "La línea que le recorre el costado puede almacenar\nluz solar. Brilla con mucha fuerza por la noche."
      },
      {
        "game": "xy-y",
        "text": "Si se expone mucho al sol, los dibujos de sus aletas\nbrillan en la oscuridad."
      },
      {
        "game": "oras-or",
        "text": "La línea que le recorre el costado puede almacenar luz solar.\nBrilla con mucha fuerza por la noche."
      },
      {
        "game": "oras-as",
        "text": "Si se expone mucho al sol, los dibujos de sus aletas brillan\nen la oscuridad."
      },
      {
        "game": "sm-s",
        "text": "Las marcas rosadas de su piel brillan con\nintensidad tras almacenar luz solar. Se cree\nque esta característica le permite camuflarse."
      },
      {
        "game": "sm-m",
        "text": "Sus dos aletas le permiten saltar fuera del agua,\nmomento que aprovechan los Wingull para\nllevárselos al buche."
      },
      {
        "game": "usum-us",
        "text": "Las marcas rosadas de su piel brillan al caer la\nnoche. Triunfa entre los buceadores, por eso en\nlos resorts turísticos le proporcionan alimento."
      },
      {
        "game": "usum-um",
        "text": "Por el día permanece cerca de la superficie y se\nretira a las profundidades por la noche. Atrae a\nlas presas con sus brillantes aletas caudales."
      }
    ]
  },
  "ita": {
    "name": "Finneon",
    "genus": "Pokémon Pescealato",
    "flavorText": [
      {
        "game": "xy-x",
        "text": "La linea che contorna il suo corpo immagazzina la\nluce solare. Di notte si illumina di una luce splendente."
      },
      {
        "game": "xy-y",
        "text": "Dopo una lunga esposizione al sole, i motivi sulle\nsue pinne brillano vividamente al calar dell’oscurità."
      },
      {
        "game": "oras-or",
        "text": "La linea che contorna il suo corpo immagazzina la luce solare.\nDi notte si illumina di una luce splendente."
      },
      {
        "game": "oras-as",
        "text": "Dopo una lunga esposizione al sole, i motivi sulle sue pinne\nbrillano vividamente al calar dell’oscurità."
      },
      {
        "game": "sm-s",
        "text": "I motivi rosa sul suo corpo brillano dopo aver\nimmagazzinato la luce solare. Pare che questa\nsia una forma di mimetismo."
      },
      {
        "game": "sm-m",
        "text": "Le pinne caudali gli permettono di saltare fuori\ndall’acqua. Spesso Wingull approfitta di questi\nmomenti per acchiapparlo al volo."
      },
      {
        "game": "usum-us",
        "text": "I motivi rosa sul suo corpo brillano di notte.\nPoiché è molto amato dai sub, alcuni centri\nturistici li attirano con il cibo."
      },
      {
        "game": "usum-um",
        "text": "Attira la preda con le sue brillanti pinne.\nDi giorno nuota vicino alla superficie del mare,\nmentre di notte si sposta in profondità."
      }
    ]
  },
  "eng": {
    "name": "Finneon",
    "genus": "Wing Fish Pokémon",
    "flavorText": [
      {
        "game": "dp-d",
        "text": "After long exposure to sunlight,\nthe patterns on its tail fins shine\nvividly when darkness arrives."
      },
      {
        "game": "dp-p",
        "text": "The way its two tail fins flutter\nwhile it swims has earned it the\nnickname “BEAUTIFLY of the Sea.”"
      },
      {
        "game": "pt",
        "text": "The line running down its side can\nstore sunlight. It shines vividly at\nnight."
      },
      {
        "game": "hgss-hg",
        "text": "Swimming and fluttering its two tail fins,\nit looks like a BEAUTIFLY. At night, the\npatterns on its tail fins softly shine."
      },
      {
        "game": "hgss-ss",
        "text": "Swimming and fluttering its two tail fins,\nit looks like a BEAUTIFLY. At night, the\npatterns on its tail fins softly shine."
      },
      {
        "game": "bw-b",
        "text": "The line running down its side can\nstore sunlight. It shines vividly at\nnight."
      },
      {
        "game": "bw-w",
        "text": "The line running down its side can\nstore sunlight. It shines vividly at\nnight."
      },
      {
        "game": "b2w2-b2",
        "text": "The line running down its side can\nstore sunlight. It shines vividly at\nnight."
      },
      {
        "game": "b2w2-w2",
        "text": "The line running down its side can\nstore sunlight. It shines vividly at\nnight."
      },
      {
        "game": "xy-x",
        "text": "The line running down its side can store sunlight.\nIt shines vividly at night."
      },
      {
        "game": "xy-y",
        "text": "After long exposure to sunlight, the patterns on its\ntail fins shine vividly when darkness arrives."
      },
      {
        "game": "oras-or",
        "text": "The line running down its side can store sunlight.\nIt shines vividly at night."
      },
      {
        "game": "oras-as",
        "text": "After long exposure to sunlight, the patterns on its\ntail fins shine vividly when darkness arrives."
      },
      {
        "game": "sm-s",
        "text": "It absorbs sunlight with the pink areas of its\nskin, which then shine. This appears to be a\nform of camouflage."
      },
      {
        "game": "sm-m",
        "text": "Its double tail fins propel its energetic jumps.\nWhen it breaks the surface of the sea, Wingull\nswoop down to grab it on the fly."
      },
      {
        "game": "usum-us",
        "text": "When night falls, their pink patterns begin to\nshine. They’re popular with divers, so there are\nresorts that feed them to keep them close."
      },
      {
        "game": "usum-um",
        "text": "It lures in prey with its shining tail fins. It stays\nnear the surface during the day and moves to\nthe depths when night falls."
      },
      {
        "game": "la",
        "text": "What a gorgeous sight this Pokémon is as it swims with its long,\npink-painted caudal fins fluttering behind it. Finneon's beautiful\nappearance has led to its nickname: ”finery fish.”"
      }
    ]
  },
  "chs": {
    "name": "荧光鱼",
    "genus": "飞翅鱼宝可梦",
    "flavorText": [
      {
        "game": "sm-s",
        "text": "粉红色的那部分皮肤\n会储存太阳光并发光。\n听说是用来做保护色的。"
      },
      {
        "game": "sm-m",
        "text": "用２片尾鳍活力四射地跳跃。\n跳出海面的那一刻，\n会被长翅鸥叼走。"
      },
      {
        "game": "usum-us",
        "text": "粉红色的花纹到了夜里就会发光。\n很受潜水者欢迎，\n所以有时会被驯养在度假地。"
      },
      {
        "game": "usum-um",
        "text": "用发光的尾鳍引诱猎物。\n白天会在海面附近，\n到了夜里就向海的深处移动。"
      }
    ]
  }
}
