{
  "id": "ledyba-f",
  "nid": "0165-f",
  "dexNum": 165,
  "formId": "f",
  "name": "Ledyba ♀",
  "psName": "Ledyba",
  "formName": "Female",
  "region": "johto",
  "generation": 4,
  "type1": "bug",
  "type2": "flying",
  "color": "red",
  "abilities": {
    "primary": "swarm",
    "secondary": "earlybird",
    "hidden": "rattled"
  },
  "isDefault": false,
  "isForm": true,
  "isLegendary": false,
  "isMythical": false,
  "isUltraBeast": false,
  "ultraBeastCode": null,
  "isSpecialAbilityForm": false,
  "isCosmeticForm": true,
  "isFemaleForm": true,
  "hasGenderDifferences": true,
  "isBattleOnlyForm": false,
  "isSwitchableForm": false,
  "isFusion": false,
  "fusedWith": null,
  "isMega": false,
  "isPrimal": false,
  "isGmax": false,
  "isRegional": false,
  "canGmax": false,
  "canDynamax": true,
  "canBeAlpha": false,
  "debutIn": "dp",
  "obtainableIn": [
    "hgss",
    "go",
    "bdsp"
  ],
  "versionExclusiveIn": [],
  "eventOnlyIn": [],
  "storableIn": [
    "dp",
    "pt",
    "hgss",
    "bw",
    "b2w2",
    "xy",
    "oras",
    "go",
    "sm",
    "usum",
    "home",
    "bdsp"
  ],
  "shinyReleased": true,
  "shinyBase": null,
  "baseStats": {
    "hp": 40,
    "atk": 20,
    "def": 30,
    "spa": 40,
    "spd": 80,
    "spe": 55
  },
  "weight": 1080,
  "height": 100,
  "baseSpecies": "ledyba",
  "baseForms": [],
  "forms": [],
  "evolvesFrom": null,
  "refs": {
    "smogon": "ledyba",
    "showdown": "ledyba",
    "serebii": "ledyba",
    "bulbapedia": "Ledyba"
  }
}
